kalabash_imap_migration/__init__.py
kalabash_imap_migration/apps.py
kalabash_imap_migration/auth_backends.py
kalabash_imap_migration/checks.py
kalabash_imap_migration/factories.py
kalabash_imap_migration/forms.py
kalabash_imap_migration/handlers.py
kalabash_imap_migration/kalmonak_extension.py
kalabash_imap_migration/models.py
kalabash_imap_migration/serializers.py
kalabash_imap_migration/settings.py
kalabash_imap_migration/tests.py
kalabash_imap_migration/urls.py
kalabash_imap_migration/urls_api.py
kalabash_imap_migration/views.py
kalabash_imap_migration/viewsets.py
kalabash_imap_migration/locale/en/LC_MESSAGES/django.mo
kalabash_imap_migration/locale/en/LC_MESSAGES/django.po
kalabash_imap_migration/locale/fr/LC_MESSAGES/django.mo
kalabash_imap_migration/locale/fr/LC_MESSAGES/django.po
kalabash_imap_migration/management/__init__.py
kalabash_imap_migration/management/commands/__init__.py
kalabash_imap_migration/management/commands/generate_offlineimap_config.py
kalabash_imap_migration/migrations/0001_initial.py
kalabash_imap_migration/migrations/0002_password.py
kalabash_imap_migration/migrations/0003_auto_20190207_0919.py
kalabash_imap_migration/migrations/0004_auto_20190207_0939.py
kalabash_imap_migration/migrations/0005_auto_20210401_0938.py
kalabash_imap_migration/migrations/__init__.py
kalabash_imap_migration/static/index.html
kalabash_imap_migration/static/kalabash_imap_migration/webpack-stats.json
kalabash_imap_migration/static/kalabash_imap_migration/css/app.246ddddb.css
kalabash_imap_migration/static/kalabash_imap_migration/css/chunk-vendors.7f89301a.css
kalabash_imap_migration/static/kalabash_imap_migration/js/app.afe0e515.js
kalabash_imap_migration/static/kalabash_imap_migration/js/chunk-vendors.5f20a268.js
kalabash_imap_migration/templates/kalabash_imap_migration/index.html
kalabash_imap_migration/templates/kalabash_imap_migration/offlineimap.conf
kalabash_imap_migration-1.3.7.dist-info/LICENSE
kalabash_imap_migration-1.3.7.dist-info/METADATA
kalabash_imap_migration-1.3.7.dist-info/WHEEL
kalabash_imap_migration-1.3.7.dist-info/top_level.txt
kalabash_imap_migration-1.3.7.dist-info/RECORD
